bauplan_cli/__init__.py
bauplan_cli/math.py
bauplan-0.0.2.dist-info/WHEEL
bauplan-0.0.2.dist-info/METADATA
bauplan-0.0.2.dist-info/RECORD
