Metadata-Version: 2.1
Name: bauplan
Version: 0.0.2
Summary: Bauplan CLI
Author: Jacopo Tagliabue
Author-email: jacopo.tagliabue@bauplanlabs.com
Requires-Python: >=3.8,<4.0
Classifier: Programming Language :: Python :: 3
Classifier: Programming Language :: Python :: 3.8
Classifier: Programming Language :: Python :: 3.9
Classifier: Programming Language :: Python :: 3.10
Classifier: Programming Language :: Python :: 3.11
